pypinonevirgin
