Metadata-Version: 2.1
Name: pypinonevirgin
Version: 0.0.2
Summary: Build my first PyPI package
Home-page: https://github.com/Jim107225017
Author: Jim Chen
Author-email: jim850212@gmail.com
Maintainer: Jim Chen
Maintainer-email: jim850212@gmail.com
License: MIT
Keywords: build your pypi
Classifier: Development Status :: 5 - Production/Stable
Classifier: Environment :: Web Environment
Classifier: Intended Audience :: Developers
Classifier: Operating System :: OS Independent
Classifier: Programming Language :: Python
Classifier: Programming Language :: Python :: 3
Classifier: Programming Language :: Python :: 3.7
Classifier: Programming Language :: Python :: 3.8
Classifier: Programming Language :: Python :: 3.9
Requires-Python: >=3.7.3
